research_roc_utils/__init__.py
research_roc_utils/roc_utils.py
research_roc_utils-0.1.1.dist-info/LICENSE
research_roc_utils-0.1.1.dist-info/METADATA
research_roc_utils-0.1.1.dist-info/WHEEL
research_roc_utils-0.1.1.dist-info/top_level.txt
research_roc_utils-0.1.1.dist-info/RECORD
